mau_tex_visitor/__init__.py
mau_tex_visitor/templates/block.tex
mau_tex_visitor/templates/block_group.tex
mau_tex_visitor/templates/callout.tex
mau_tex_visitor/templates/callouts_entry.tex
mau_tex_visitor/templates/command.tex
mau_tex_visitor/templates/container.tex
mau_tex_visitor/templates/content.tex
mau_tex_visitor/templates/content_image.tex
mau_tex_visitor/templates/document.tex
mau_tex_visitor/templates/footnote.tex
mau_tex_visitor/templates/footnotes.tex
mau_tex_visitor/templates/footnotes_entry.tex
mau_tex_visitor/templates/header.tex
mau_tex_visitor/templates/horizontal_rule.tex
mau_tex_visitor/templates/list.tex
mau_tex_visitor/templates/list_item.tex
mau_tex_visitor/templates/macro.tex
mau_tex_visitor/templates/paragraph.tex
mau_tex_visitor/templates/raw.tex
mau_tex_visitor/templates/sentence.tex
mau_tex_visitor/templates/source.tex
mau_tex_visitor/templates/text.tex
mau_tex_visitor/templates/toc_entry.tex
mau_tex_visitor/templates/tox.tex
mau_tex_visitor/templates/verbatim.tex
mau_tex_visitor/templates/block/admonition.tex
mau_tex_visitor/templates/block/quote.tex
mau_tex_visitor/templates/macro/class.tex
mau_tex_visitor/templates/macro/image.tex
mau_tex_visitor/templates/macro/link.tex
mau_tex_visitor/templates/style/caret.tex
mau_tex_visitor/templates/style/star.tex
mau_tex_visitor/templates/style/tilde.tex
mau_tex_visitor/templates/style/underscore.tex
mau_tex_visitor-2.0.1.dist-info/entry_points.txt
mau_tex_visitor-2.0.1.dist-info/LICENSE
mau_tex_visitor-2.0.1.dist-info/WHEEL
mau_tex_visitor-2.0.1.dist-info/METADATA
mau_tex_visitor-2.0.1.dist-info/RECORD
